LICENSE
MANIFEST.in
README.md
setup.cfg
setup.py
./cpss_facebook/__init__.py
./cpss_facebook/admin.py
./cpss_facebook/apps.py
./cpss_facebook/asgi.py
./cpss_facebook/models.py
./cpss_facebook/settings.py
./cpss_facebook/signals.py
./cpss_facebook/tests.py
./cpss_facebook/urls.py
./cpss_facebook/views.py
./cpss_facebook/wsgi.py
./cpss_facebook/migrations/0001_initial.py
./cpss_facebook/migrations/__init__.py
cpss_facebook/static/.gitkeep
cpss_facebook/static/cpss/logo.png
cpss_facebook/templates/.gitkeep
django_cpss_facebook.egg-info/PKG-INFO
django_cpss_facebook.egg-info/SOURCES.txt
django_cpss_facebook.egg-info/dependency_links.txt
django_cpss_facebook.egg-info/top_level.txt
docs/.gitkeep