Metadata-Version: 2.1
Name: django-cpss-facebook
Version: 1.2.0
Summary: This is the Django component that helps to integrate aspects of facebook into your application.
Home-page: https://github.com/xgdfalcon/django-cpss-facebook/
Author: CPSS by XGDFalcon®
Author-email: xgdfalcon@gmail.com
License: MIT
Platform: UNKNOWN
Classifier: Environment :: Web Environment
Classifier: Framework :: Django
Classifier: Intended Audience :: Developers
Classifier: License :: OSI Approved :: Apache Software License
Classifier: Operating System :: OS Independent
Classifier: Programming Language :: Python
Classifier: Programming Language :: Python :: 3
Classifier: Programming Language :: Python :: 3 :: Only
Classifier: Programming Language :: Python :: 3.6
Classifier: Programming Language :: Python :: 3.7
Classifier: Programming Language :: Python :: 3.8
